command_mk2/__init__.py
command_mk2/filter.py
command_mk2-0.1.2.dist-info/LICENSE
command_mk2-0.1.2.dist-info/METADATA
command_mk2-0.1.2.dist-info/WHEEL
command_mk2-0.1.2.dist-info/RECORD
