Metadata-Version: 2.1
Name: command_mk2
Version: 0.1.2
Summary: Custom version of Command filter for aiogram 3
Home-page: https://github.com/AbstractiveNord/CommandMk2
License: MIT
Keywords: aiogram,filter,command,commandmk2,command_mk2
Author: Aleksandr Antonov
Requires-Python: >=3.10,<4.0
Classifier: License :: OSI Approved :: MIT License
Classifier: Programming Language :: Python :: 3
Classifier: Programming Language :: Python :: 3.10
Classifier: Programming Language :: Python :: 3.11
Classifier: Programming Language :: Python :: 3.12
Requires-Dist: aiogram (>=3.0.0b5,<4.0.0)
Project-URL: Documentation, https://commandmk2.readthedocs.io/en/latest/
Project-URL: Repository, https://github.com/AbstractiveNord/CommandMk2
